setup.py
PyQt5_Auto/__init__.py
PyQt5_Auto.egg-info/PKG-INFO
PyQt5_Auto.egg-info/SOURCES.txt
PyQt5_Auto.egg-info/dependency_links.txt
PyQt5_Auto.egg-info/top_level.txt