Metadata-Version: 1.0
Name: PyQt5-Auto
Version: 0.0.0
Summary: 自动配置PyQt5环境/setup PyQt5 environment automatically
Home-page: UNKNOWN
Author: Ruoyu Wang
Author-email: wry2022@outlook.com
License: UNKNOWN
Platform: UNKNOWN
